pkg_publisher/__init__.py
pkg_publisher/__main__.py
pkg_publisher/executors.py
pkg_publisher/server.py
pkg_publisher/service.py
pkg_publisher/streaming_buffer.py
pkg_publisher-0.1.6.dist-info/licenses/LICENSE
pkg_publisher-0.1.6.dist-info/METADATA
pkg_publisher-0.1.6.dist-info/WHEEL
pkg_publisher-0.1.6.dist-info/entry_points.txt
pkg_publisher-0.1.6.dist-info/top_level.txt
pkg_publisher-0.1.6.dist-info/RECORD
