Metadata-Version: 2.4
Name: pkg-publisher
Version: 0.1.6
Summary: A Model Context Protocol (MCP) service for building and publishing Python packages to PyPI
Author-email: pkg-publisher contributors <maintainer@example.com>
License: MIT
Project-URL: Homepage, https://github.com/username/pkg-publisher
Project-URL: Repository, https://github.com/username/pkg-publisher
Project-URL: Documentation, https://github.com/username/pkg-publisher/blob/main/README.md
Classifier: Development Status :: 3 - Alpha
Classifier: Intended Audience :: Developers
Classifier: License :: OSI Approved :: MIT License
Classifier: Programming Language :: Python :: 3
Classifier: Programming Language :: Python :: 3.8
Classifier: Programming Language :: Python :: 3.9
Classifier: Programming Language :: Python :: 3.10
Classifier: Programming Language :: Python :: 3.11
License-File: LICENSE
Requires-Dist: fastmcp>=0.1.0
Requires-Dist: pydantic>=2.0.0
Requires-Dist: build>=0.10.0
Requires-Dist: twine>=4.0.0
Requires-Dist: requests>=2.31.0
Requires-Dist: pywinpty>=2.0.0; sys_platform == "win32"
Provides-Extra: dev
Requires-Dist: pytest>=7.0.0; extra == "dev"
Requires-Dist: black>=23.0.0; extra == "dev"
Requires-Dist: flake8>=6.0.0; extra == "dev"
Dynamic: license-file
